veridex/__init__.py
veridex/audio/__init__.py
veridex/audio/aasist_signal.py
veridex/audio/breathing_signal.py
veridex/audio/silence.py
veridex/audio/spectral.py
veridex/audio/utils.py
veridex/audio/wav2vec_signal.py
veridex/core/__init__.py
veridex/core/provenance.py
veridex/core/signal.py
veridex/eval/__init__.py
veridex/eval/dataset.py
veridex/eval/metrics.py
veridex/eval/runner.py
veridex/image/__init__.py
veridex/image/clip.py
veridex/image/dire.py
veridex/image/ela.py
veridex/image/frequency.py
veridex/image/mlep.py
veridex/text/__init__.py
veridex/text/binoculars.py
veridex/text/detectgpt.py
veridex/text/entropy.py
veridex/text/human_ood.py
veridex/text/perplexity.py
veridex/text/stylometry.py
veridex/text/tdetect.py
veridex/utils/__init__.py
veridex/utils/confidence.py
veridex/utils/downloads.py
veridex/video/__init__.py
veridex/video/ensemble.py
veridex/video/i3d.py
veridex/video/lipsync.py
veridex/video/processing.py
veridex/video/rppg.py
veridex/video/utils.py
veridex/video/weights.py
veridex/video/models/__init__.py
veridex/video/models/i3d.py
veridex/video/models/physnet.py
veridex/video/models/syncnet.py
veridex-0.2.0.dist-info/licenses/LICENSE
veridex-0.2.0.dist-info/METADATA
veridex-0.2.0.dist-info/WHEEL
veridex-0.2.0.dist-info/top_level.txt
veridex-0.2.0.dist-info/RECORD
