Metadata-Version: 2.4
Name: veridex
Version: 0.2.0
Summary: A modular, probabilistic, and research-grounded AI content detection library.
Home-page: https://github.com/ADITYAMAHAKALI/veridex
Author: Veridex Contributors
Author-email: adityamahakali@aisolve.org
License:                                  Apache License
Project-URL: Homepage, https://github.com/ADITYAMAHAKALI/veridex
Project-URL: Bug Tracker, https://github.com/ADITYAMAHAKALI/veridex/issues
Requires-Python: >=3.9
License-File: LICENSE
Requires-Dist: numpy>=1.20.0
Requires-Dist: scipy>=1.7.0
Requires-Dist: pydantic>=2.0.0
Provides-Extra: text
Requires-Dist: transformers>=4.30.0; extra == "text"
Requires-Dist: torch>=2.0.0; extra == "text"
Requires-Dist: nltk>=3.8; extra == "text"
Provides-Extra: image
Requires-Dist: torch>=2.0.0; extra == "image"
Requires-Dist: torchvision>=0.15.0; extra == "image"
Requires-Dist: diffusers>=0.20.0; extra == "image"
Requires-Dist: Pillow>=9.0.0; extra == "image"
Requires-Dist: opencv-python-headless>=4.0.0; extra == "image"
Provides-Extra: audio
Requires-Dist: torch>=2.0.0; extra == "audio"
Requires-Dist: torchaudio>=2.0.0; extra == "audio"
Requires-Dist: transformers>=4.30.0; extra == "audio"
Requires-Dist: librosa>=0.10.0; extra == "audio"
Requires-Dist: soundfile>=0.12.0; extra == "audio"
Provides-Extra: dev
Requires-Dist: pytest>=7.0.0; extra == "dev"
Requires-Dist: black>=23.0.0; extra == "dev"
Requires-Dist: flake8>=6.0.0; extra == "dev"
Requires-Dist: mypy>=1.0.0; extra == "dev"
Provides-Extra: docs
Requires-Dist: mkdocs>=1.5.0; extra == "docs"
Requires-Dist: mkdocs-material>=9.0.0; extra == "docs"
Requires-Dist: mkdocstrings[python]>=0.24.0; extra == "docs"
Provides-Extra: video
Requires-Dist: torch>=2.0.0; extra == "video"
Requires-Dist: torchvision>=0.15.0; extra == "video"
Requires-Dist: opencv-python-headless>=4.0.0; extra == "video"
Requires-Dist: scipy>=1.7.0; extra == "video"
Requires-Dist: librosa>=0.10.0; extra == "video"
Requires-Dist: mediapipe>=0.10.0; extra == "video"
Dynamic: author-email
Dynamic: home-page
Dynamic: license-file
Dynamic: requires-python
